{
  "type": "tutorial",
  "title": "5 Ways You Can Make Motion Graphics in Blender Today!",
  "url": "https://www.youtube.com/watch?v=EdNwfKW1umU",
  "platform": "youtube",
  "priceType": "free",
  "creator": "Ducky 3D",
  "language": "en",
  "level": [
    "intermediate"
  ],
  "categories": [
    "motion_design"
  ],
  "goals": [],
  "duration": "6分",
  "recommendedOrder": null,
  "summary": "5 Ways You Can Make Motion Graphics in Blender Today — a Blender motion design / geometry nodes tutorial by Ducky 3D.",
  "comment": null,
  "affiliateUrl": null,
  "isAffiliate": false,
  "isPr": false,
  "updatedAt": "2026-05-15",
  "status": "active",
  "publishedAt": "2023-05-16",
  "blenderVersion": null
}
