{
  "type": "tutorial",
  "title": "Armored All Might Chibi in Blender 3D Timelapse",
  "url": "https://www.youtube.com/watch?v=OoFnqXPRrWk",
  "platform": "youtube",
  "priceType": "free",
  "creator": "adiidiin",
  "language": "en",
  "level": [
    "intermediate"
  ],
  "categories": [
    "modeling"
  ],
  "goals": [],
  "duration": "21分",
  "recommendedOrder": null,
  "summary": "Armored All Might Chibi in Blender 3D Timelapse — a Blender character modeling / sculpting & toon-shader tutorial by adiidiin.",
  "comment": null,
  "affiliateUrl": null,
  "isAffiliate": false,
  "isPr": false,
  "updatedAt": "2026-05-15",
  "status": "active",
  "publishedAt": null,
  "blenderVersion": null
}
