{
  "type": "tutorial",
  "title": "Blender Character Creation: Sirius Black Timelapse Part 2/3",
  "url": "https://www.youtube.com/watch?v=X8CdQqPt2mc",
  "platform": "youtube",
  "priceType": "free",
  "creator": "adiidiin",
  "language": "en",
  "level": [
    "intermediate"
  ],
  "categories": [
    "modeling"
  ],
  "goals": [],
  "duration": "9分",
  "recommendedOrder": null,
  "summary": "Blender Character Creation: Sirius Black Timelapse Part 2/3 — a Blender character modeling / sculpting & toon-shader tutorial by adiidiin.",
  "comment": null,
  "affiliateUrl": null,
  "isAffiliate": false,
  "isPr": false,
  "updatedAt": "2026-05-15",
  "status": "active",
  "publishedAt": null,
  "blenderVersion": null
}
